{
	"plugin_name": "text-with-side",
	"releases": [
		{
			"version": "1.0.0",
			"date": "2024-01-01",
			"type": "release",
			"title": "Первоначальный релиз",
			"description": "Первый стабильный релиз плагина Text with Side",
			"changes": {
				"added": [
					"Создан гутенберговский блок для текста с боковым изображением",
					"Добавлен полноценный текстовый редактор с поддержкой форматирования",
					"Реализована возможность добавления и удаления изображений",
					"Добавлена настройка позиции изображения (слева/справа)",
					"Реализованы три варианта ссылок на изображение (нет, на медиафайл, на страницу вложения)",
					"Добавлена настройка ширины блока изображения",
					"Создана полная локализация на русский и английский языки",
					"Реализована адаптивная верстка для мобильных устройств",
					"Добавлены стили для редактора и фронтенда",
					"Создана система безопасности с проверкой прав доступа"
				],
				"changed": [],
				"fixed": [],
				"deprecated": [],
				"removed": [],
				"security": []
			}
		}
	],
	"current_version": "1.0.0",
	"last_updated": "2024-01-01",
	"plugin_info": {
		"name": "Text with Side",
		"description": "Гутенберговский блок для текста с боковым изображением",
		"author": "Владимир Бычко",
		"author_uri": "http://bychko.ru",
		"text_domain": "text-with-side",
		"domain_path": "/languages"
	}
}